spyraio/__about__.py
spyraio/__init__.py
spyraio/spyraio.py
spyraio/classification/DecisionTree.py
spyraio/classification/MLP.py
spyraio/classification/SVM.py
spyraio/classification/__init__.py
spyraio/classification/model.py
spyraio/preprocessing/__init__.py
spyraio/preprocessing/dataframe.py
spyraio/utils/__init__.py
spyraio/utils/utils.py
spyraio/visualization/__init__.py
spyraio/visualization/metrics.py
spyraio-0.0.14.dist-info/LICENSE
spyraio-0.0.14.dist-info/METADATA
spyraio-0.0.14.dist-info/WHEEL
spyraio-0.0.14.dist-info/top_level.txt
spyraio-0.0.14.dist-info/RECORD
