Metadata-Version: 2.1
Name: spyraio
Version: 0.0.14
Summary: Spyraio it's a Python package which contains some functions to lightning forecasting.
Home-page: https://github.com/AdrianoPereira/spyraio
Author: Adriano P. Almeida
Author-email: adriano.almeida@inpe.br
License: MIT
Keywords: weather lightning nowcasting meteorology radar
Platform: UNKNOWN
Requires-Dist: numpy
Requires-Dist: matplotlib
